{
    "localization": {
        "driveBase": 31.29,
        "trackWidth": 33.53,
        "odometryCyclesPerRevolution": 360,
        "fieldSideLength": 365.76,
        "odometryWheelRadius": 2.9,
        "odometryPoses": {
            "xL": [
                4.445,
                18.415,
                0
            ],
            "y": [
                -3.4925,
                -18.0975,
                90
            ],
            "xR": [
                4.445,
                -19.05,
                0
            ]
        }
    },
    "io": {"resPrefix": "\\HyperiLibs\\src\\main\\res"},
    "spline": {
        "verbose": false,
        "bisectionError": 0.01,
        "segmentLength": 50,
        "integrator": {
            "n": 2,
            "relAcc": 1e-1,
            "absAcc": 1e-2,
            "minIters": 1,
            "maxIters": 8
        }
    },
    "motionProfile": {
        "verbose": true,
        "endErrorThresholds": {
            "rotation": 0.0174533,
            "translation": 1
        },
        "k": {
            "kAv": 0,
            "kTa": 0.01467,
            "kAa": 0,
            "kTv": 0.002857
        },
        "maxes": {
            "aVel": 12.566,
            "tAcc": 100,
            "tVel": 150
        }
    },
    "teamcode": {
        "forceEndTimeLeft": 3500,
        "metricsDelay": 100,
        "localizationDelay": 10
    },
    "pid": {
        "x": {
            "kP": 0.025,
            "kD": 0.23,
            "kI": 1.0E-4
        },
        "y": {
            "kP": 0.03,
            "kD": 0.01,
            "kI": 7.0E-5
        },
        "theta": {
            "kP": 0.5,
            "kD": 0.16,
            "kI": 1.0E-5
        }
    },
    "dashboard": {
        "isDebugging": false,
        "gui": {
            "sizes": {
                "waypoint": 24,
                "planningPoint": 4.5
            },
            "wbb": {
                "strokeWidth": 4,
                "grayScale": 0.3
            },
            "dragTime": 150
        },
        "net": {"serviceUUID": "2d26618601fb47c28d9f10b8ec891363"},
        "version": "4.1"
    }
}